cyber_down/__init__.py
cyber_down/handlers/__init__.py
cyber_down/handlers/configs.py
cyber_down/handlers/constants.py
cyber_down/handlers/decorators.py
cyber_down/handlers/download_metrics.py
cyber_down/handlers/downloaders.py
cyber_down/handlers/process_chunks.py
cyber_down/resolver/__init__.py
cyber_down/resolver/batch_file_resolver.py
cyber_down/resolver/logs/decorators_20251022.log
cyber_down/resolver/logs/downloaders_20251022.log
cyber_down/resolver/logs/process_chunks_20251022.log
cyber_down/resolver/logs/start_download_20251022.log
cyber_down/resolver/single_file_resolver.py
cyber_down/start_download.py
cyber_down-0.1.3.dist-info/licenses/LICENSE
cyber_down-0.1.3.dist-info/WHEEL
cyber_down-0.1.3.dist-info/entry_points.txt
cyber_down-0.1.3.dist-info/METADATA
cyber_down-0.1.3.dist-info/RECORD
