Metadata-Version: 2.4
Name: cyber_down
Version: 0.1.3
Summary: A tool that uses parallel segmented downloading to speed up downloads.
License-Expression: MIT
License-File: LICENSE
Classifier: Programming Language :: Python :: 3
Classifier: Operating System :: OS Independent
Requires-Dist: alive-progress>=3.3.0
Requires-Dist: httpcore>=1.0.9
Requires-Dist: requests>=2.32.5
Requires-Dist: rich>=14.2.0
Requires-Dist: typer>=0.20.0
Requires-Dist: update>=0.0.1
Requires-Dist: uv-build>=0.9.17
Requires-Python: >=3.10
Project-URL: Homepage, https://github.com/Cyber-Smoke/cyber_down
Project-URL: Issues, https://github.com/Cyber-Smoke/cyber_down/issues
